{
	"$schema": "https://schemas.wp.org/trunk/theme.json",
	"version": 3,
	"settings": {
		"appearanceTools": true,
		"border": {
			"radius": false,
			"color": false,
			"style": false,
			"width": false
		},
		"color": {
			"custom": false,
			"customDuotone": false,
			"customGradient": false,
			"defaultDuotone": false,
			"defaultGradients": false,
			"defaultPalette": false,
			"duotone": [
				{
					"colors": [ "#000000", "#FFFFFF" ],
					"slug": "black-and-white",
					"name": "Black and white"
				}
			],
			"gradients": [],
			"palette": [
				{
					"name": "Brand",
					"slug": "primary",
					"color": "#5344F4"
				},
				{
					"name": "Brand Accent",
					"slug": "primary-accent",
					"color": "#e9e7ff"
				},
				{
					"name": "Brand Alt",
					"slug": "primary-alt",
					"color": "#DEC9FF"
				},
				{
					"name": "Brand Alt Accent",
					"slug": "primary-alt-accent",
					"color": "#3d386b"
				},
				{
					"name": "Contrast",
					"slug": "main",
					"color": "#1E1E26"
				},
				{
					"name": "Contrast Accent",
					"slug": "main-accent",
					"color": "#d4d4ec"
				},
				{
					"name": "Base",
					"slug": "base",
					"color": "#fff"
				},
				{
					"name": "Base Accent",
					"slug": "secondary",
					"color": "#545473"
				},
				{
					"name": "Tint",
					"slug": "tertiary",
					"color": "#f8f7fc"
				},
				{
					"name": "Border Base",
					"slug": "border-light",
					"color": "#E3E3F0"
				},
				{
					"name": "Border Contrast",
					"slug": "border-dark",
					"color": "#4E4E60"
				}
			],
			"link": false
		},
		"custom": {
			"fontWeight": {
				"normal": 400,
				"semi-bold": 600,
				"bold": 700
			},
			"lineHeight": {
				"tight": 1.25,
				"snug": 1.333,
				"base": 1.4,
				"relaxed": 1.5
			}
		},
		"layout": {
			"contentSize": "788px",
			"wideSize": "1200px"
		},
		"shadow": {
			"defaultPresets": false
        },
		"spacing": {
			"customSpacingSize": false,
			"defaultSpacingSizes": false,
			"spacingSizes": [
				{
					"name": "Small",
					"size": "clamp(.5rem, 2.5vw, 1rem)",
					"slug": "small"
				},
				{
					"name": "Medium",
					"size": "clamp(1.5rem, 4vw, 2rem)",
					"slug": "medium"
				},
				{
					"name": "Large",
					"size": "clamp(2rem, 5vw, 3rem)",
					"slug": "large"
				},
				{
					"name": "Extra Large",
					"size": "clamp(3rem, 7vw, 5rem)",
					"slug": "x-large"
				},
				{
					"name": "2xl",
					"size": "clamp(4rem, 9vw, 7rem)",
					"slug": "xx-large"
				},
				{
					"name": "3xl",
					"size": "clamp(5rem, 12vw, 9rem)",
					"slug": "xxx-large"
				},
				{
					"name": "4xl",
					"size": "clamp(6rem, 14vw, 13rem)",
					"slug": "xxxx-large"
				}
			],
			"blockGap": true,
			"padding": true,
			"margin": true
		},
		"typography": {
			"customFontSize": false,
			"dropCap": false,
			"defaultFontSizes": false,
			"fluid": true,
			"fontFamilies": [
				{
					"fontFace": [
						{
							"fontDisplay": "swap",
							"fontFamily": "Inter",
							"fontStyle": "normal",
							"fontWeight": "400 700",
							"src": [
								"file:./assets/src/fonts/inter.ttf"
							]
						},
						{
							"fontDisplay": "swap",
							"fontFamily": "Inter",
							"fontStyle": "italic",
							"fontWeight": "400 700",
							"src": [
								"file:./assets/src/fonts/inter-italic.ttf"
							]
						}
					],
					"fontFamily": "Inter, sans-serif",
					"name": "Default (Inter)",
					"slug": "default"
				},
				{
					"fontFace": [
						{
							"fontDisplay": "swap",
							"fontFamily": "Montserrat",
							"fontStyle": "normal",
							"fontWeight": "400 700",
							"src": [
								"file:./assets/src/fonts/montserrat.ttf"
							]
						}
					],
					"fontFamily": "Montserrat, Inter, sans-serif",
					"name": "Display (Montserrat)",
					"slug": "display"
				}
			],
			"fontSizes": [
				{
					"size": "0.75rem",
					"slug": "x-small",
					"name": "Body: Extra Small"
				},
				{
					"size": "0.875rem",
					"slug": "small",
					"name": "Body: Small"
				},
				{
					"size": "1rem",
					"slug": "medium",
					"name": "Body: Medium"
				},
				{
					"fluid": {
						"min": "1.125rem",
						"max": "1.25rem"
					},
					"size": "1.25rem",
					"slug": "large",
					"name": "Body: Large"
				},
				{
					"fluid": {
						"min": "1.25rem",
						"max": "1.5rem"
					},
					"size": "1.5rem",
					"slug": "header-3",
					"name": "Title: Header 3"
				},
				{
					"fluid": {
						"min": "1.5rem",
						"max": "2rem"
					},
					"size": "2rem",
					"slug": "header-2",
					"name": "Title: Header 2"
				},
				{
					"fluid": {
						"min": "2rem",
						"max": "3rem"
					},
					"size": "3rem",
					"slug": "header-1",
					"name": "Title: Header 1"
				}
			],
			"lineHeight": true
		},
		"useRootPaddingAwareAlignments": true
	},
	"styles": {
		"blocks": {
			"core/navigation": {
				"typography": {
					"fontWeight": "500"
				},
				"elements": {
					"link": {
						":hover": {
							"typography": {
								"textDecoration": "underline"
							}
						}
					}
				}
			},
			"core/paragraph": {
				"css": "&.has-background { padding: var(--wp--preset--spacing--small) }"
			},
			"core/quote": {
				"elements": {
					"cite": {
						"typography": {
							"fontSize": "var:preset|font-size|small"
						},
						"color": {
							"text": "var:preset|color|secondary"
						}
					}
				},
				"css": "& :where(cite) { display: block }",
				"border": {
					"radius": "0",
					"style": "solid",
					"width": "0 0 0 5px !important",
					"color": "var:preset|color|primary"
				},
				"spacing": {
					"padding": {
						"left": "var:preset|spacing|large",
						"right": "var:preset|spacing|large"
					}
				},
				"typography": {
					"lineHeight": "var:custom|line-height|body",
					"fontSize": "var:preset|font-size|medium",
					"fontWeight": "500"
				}
			},
			"core/search": {
				"css": ".wp-block-search__button-inside .wp-block-search__inside-wrapper { border: none }"
			},
			"core/separator": {
				"color": {
					"text": "var:preset|color|main"
				}
			},
			"core/site-tagline": {
				"spacing": {
					"margin": {
						"bottom": "20px"
					}
				},
				"typography": {
					"fontSize": "var:preset|font-size|small"
				}
			},
			"core/site-title": {
				"typography": {
					"fontSize": "var:preset|font-size|base",
					"fontWeight": "600",
					"lineHeight": "var:custom|line-height|none",
					"letterSpacing": "0"
				},
				"elements": {
					"link": {
						"typography": {
							"textDecoration": "none"
						}
					}
				}
			},
			"core/table": {
				"typography": {
					"fontSize": "var:preset|font-size|small"
				}
			}
		},
		"color": {
			"background": "var:preset|color|base",
			"text": "var:preset|color|main"
		},
		"elements": {
			"button": {
				"border": {
					"radius": "5px",
					"width": "0"
				},
				"color": {
					"background": "var:preset|color|main",
					"text": "var:preset|color|base"
				},
				"spacing": {
					"padding": {
						"top": ".6em",
						"right": "1em",
						"bottom": ".6em",
						"left": "1em"
					}
				},
				"typography": {
					"fontSize": "var:preset|font-size|small",
					"fontWeight": "500"
				},
				":hover": {
					"color": {
						"background": "var:preset|color|main",
						"text": "var:preset|color|base"
					},
					"typography": {
						"textDecoration": "underline"
					}
				}
			},
			"h1": {
				"typography": {
					"fontSize": "var:preset|font-size|header-1",
					"lineHeight": "var:custom|line-height|snug"
        }
			},
			"h2": {
				"typography": {
					"fontSize": "var:preset|font-size|header-2",
					"lineHeight": "var:custom|line-height|snug"
				}
			},
			"h3": {
				"typography": {
					"fontSize": "var:preset|font-size|header-3"
				}
			},
			"h4": {
				"typography": {
					"fontSize": "var:preset|font-size|header-3",
          "fontWeight": "var:custom|font-weight|semi-bold"
				}
			},
			"h5": {
				"typography": {
					"fontSize": "var:preset|font-size|header-3",
          "fontWeight": "var:custom|font-weight|normal"
				}
			},
			"h6": {
				"typography": {
					"fontSize": "var:preset|font-size|body-large"
				}
			},
			"heading": {
				"typography": {
					"fontFamily": "var:preset|font-family|display",
					"fontWeight": "var:custom|font-weight|bold"
				}
			},
			"link": {
				"color": {
					"text": "var:preset|color|main"
				}
			}
		},
		"spacing": {
			"blockGap": "var:preset|spacing|medium",
			"padding": {
				"top": "0",
				"right": "var:preset|spacing|medium",
				"bottom": "0",
				"left": "var:preset|spacing|medium"
			}
		},
		"typography": {
			"fontFamily": "var:preset|font-family|default",
			"fontSize": "var:preset|font-size|large",
			"fontWeight": "var:custom|font-weight|normal",
			"lineHeight": "var:custom|line-height|base"
		}
	},
	"templateParts": [
		{
			"name": "header",
			"title": "Header",
			"area": "header"
		},
		{
			"name": "footer",
			"title": "Footer",
			"area": "footer"
		}
	]
}
